lzf.cp313-win32.pyd
python_neo_lzf-0.3.5.dist-info/licenses/LICENSE
python_neo_lzf-0.3.5.dist-info/METADATA
python_neo_lzf-0.3.5.dist-info/WHEEL
python_neo_lzf-0.3.5.dist-info/top_level.txt
python_neo_lzf-0.3.5.dist-info/RECORD
